src/__init__.py
src/parse-le-beacon.py
parse_le_beacon-0.1.0.dist-info/LICENSE
parse_le_beacon-0.1.0.dist-info/METADATA
parse_le_beacon-0.1.0.dist-info/WHEEL
parse_le_beacon-0.1.0.dist-info/entry_points.txt
parse_le_beacon-0.1.0.dist-info/top_level.txt
parse_le_beacon-0.1.0.dist-info/RECORD
