Metadata-Version: 2.1
Name: parse-le-beacon
Version: 0.1.0
Summary: Bluetooth Beacon Parser
Home-page: https://github.com/thyrasec/parse-le-beacon
Author: Thyrasec
Author-email: Thyrasec <security@thyrasec.com>
Maintainer-email: Thyrasec <security@thyrasec.com>
Project-URL: Homepage, https://github.com/thyrasec/parse-le-beacon
Project-URL: Bug Reports, https://github.com/thyrasec/parse-le-beacon/issues
Project-URL: Funding, https://donate.pypi.org
Project-URL: Say Thanks!, http://saythanks.io/to/example
Project-URL: Source, https://github.com/thyrasec/parse-le-beacon
Keywords: bluetooth,bluetooth le,setuptools,development
Classifier: Development Status :: 4 - Beta
Classifier: Intended Audience :: Developers
Classifier: Topic :: Software Development :: Build Tools
Classifier: License :: OSI Approved :: MIT License
Classifier: Programming Language :: Python :: 3
Classifier: Programming Language :: Python :: 3.7
Classifier: Programming Language :: Python :: 3.8
Classifier: Programming Language :: Python :: 3.9
Classifier: Programming Language :: Python :: 3.10
Classifier: Programming Language :: Python :: 3.11
Classifier: Programming Language :: Python :: 3 :: Only
Requires-Python: >=3.7
License-File: LICENSE
Provides-Extra: dev
Requires-Dist: check-manifest ; extra == 'dev'
Provides-Extra: test
Requires-Dist: coverage ; extra == 'test'
